{
  "update_time": "2026-05-26 18:20:20",
  "data_source": "Tushare Pro",
  "etf_list": {
    "515220.SH": {
      "name": "煤炭ETF",
      "layer": "core",
      "category": "能源",
      "latest": {
        "date": "2026-05-26",
        "open": 1.205,
        "close": 1.206,
        "high": 1.228,
        "low": 1.197,
        "volume": 4772594,
        "amount": 574923.16
      },
      "change_pct": -0.99,
      "metrics": {
        "ma5": 1.2046,
        "ma10": 1.2195,
        "ma20": 1.2472,
        "volatility_20d": 3.23
      }
    },
    "512400.SH": {
      "name": "有色金属ETF",
      "layer": "core",
      "category": "有色",
      "latest": {
        "date": "2026-05-26",
        "open": 2.009,
        "close": 2.095,
        "high": 2.1,
        "low": 1.984,
        "volume": 8702050,
        "amount": 1788917.61
      },
      "change_pct": 3.46,
      "metrics": {
        "ma5": 2.0142,
        "ma10": 2.0439,
        "ma20": 2.0981,
        "volatility_20d": 4.17
      }
    },
    "518880.SH": {
      "name": "黄金ETF",
      "layer": "core",
      "category": "贵金属",
      "latest": {
        "date": "2026-05-26",
        "open": 9.481,
        "close": 9.454,
        "high": 9.487,
        "low": 9.442,
        "volume": 2208614,
        "amount": 2089349.18
      },
      "change_pct": -0.61,
      "metrics": {
        "ma5": 9.4488,
        "ma10": 9.5425,
        "ma20": 9.6678,
        "volatility_20d": 1.8
      }
    },
    "159972.SZ": {
      "name": "5年地债ETF",
      "layer": "core",
      "category": "债券",
      "latest": {
        "date": "2026-05-26",
        "open": 119.096,
        "close": 119.124,
        "high": 119.126,
        "low": 119.076,
        "volume": 180758,
        "amount": 2152828.51
      },
      "change_pct": 0.04,
      "metrics": {
        "ma5": 119.0418,
        "ma10": 118.9684,
        "ma20": 118.8175,
        "volatility_20d": 0.15
      }
    },
    "512480.SH": {
      "name": "半导体ETF",
      "layer": "satellite",
      "category": "科技-算力",
      "latest": {
        "date": "2026-05-26",
        "open": 2.344,
        "close": 2.321,
        "high": 2.344,
        "low": 2.247,
        "volume": 11334557,
        "amount": 2594804.09
      },
      "change_pct": -1.15,
      "metrics": {
        "ma5": 2.2434,
        "ma10": 2.1572,
        "ma20": 2.0048,
        "volatility_20d": 9.71
      }
    },
    "515880.SH": {
      "name": "通信ETF",
      "layer": "satellite",
      "category": "科技-光模块",
      "latest": {
        "date": "2026-05-26",
        "open": 1.546,
        "close": 1.548,
        "high": 1.559,
        "low": 1.518,
        "volume": 19446060,
        "amount": 2994108.16
      },
      "change_pct": -0.9,
      "metrics": {
        "ma5": 1.5144,
        "ma10": 1.5201,
        "ma20": 1.4526,
        "volatility_20d": 5.99
      }
    },
    "159819.SZ": {
      "name": "人工智能ETF",
      "layer": "satellite",
      "category": "科技-AI应用",
      "latest": {
        "date": "2026-05-26",
        "open": 2.055,
        "close": 2.043,
        "high": 2.055,
        "low": 2.006,
        "volume": 4382675,
        "amount": 889884.31
      },
      "change_pct": -0.58,
      "metrics": {
        "ma5": 2.0018,
        "ma10": 1.9933,
        "ma20": 1.911,
        "volatility_20d": 5.71
      }
    },
    "516510.SH": {
      "name": "云计算ETF",
      "layer": "satellite",
      "category": "科技-云服务",
      "latest": {
        "date": "2026-05-26",
        "open": 1.858,
        "close": 1.84,
        "high": 1.858,
        "low": 1.81,
        "volume": 751704,
        "amount": 137780.25
      },
      "change_pct": -1.5,
      "metrics": {
        "ma5": 1.848,
        "ma10": 1.8856,
        "ma20": 1.8735,
        "volatility_20d": 3.05
      }
    },
    "512660.SH": {
      "name": "军工ETF",
      "layer": "satellite",
      "category": "军工",
      "latest": {
        "date": "2026-05-26",
        "open": 1.369,
        "close": 1.348,
        "high": 1.369,
        "low": 1.328,
        "volume": 2586208,
        "amount": 346828.86
      },
      "change_pct": -2.03,
      "metrics": {
        "ma5": 1.3578,
        "ma10": 1.3833,
        "ma20": 1.4036,
        "volatility_20d": 3.3
      }
    },
    "516020.SH": {
      "name": "化工ETF",
      "layer": "satellite",
      "category": "化工",
      "latest": {
        "date": "2026-05-26",
        "open": 0.899,
        "close": 0.912,
        "high": 0.915,
        "low": 0.886,
        "volume": 2214647,
        "amount": 199743.6
      },
      "change_pct": 1.33,
      "metrics": {
        "ma5": 0.9168,
        "ma10": 0.9331,
        "ma20": 0.9635,
        "volatility_20d": 3.89
      }
    },
    "510300.SH": {
      "name": "沪深300ETF",
      "layer": "hedge",
      "category": "宽基",
      "latest": {
        "date": "2026-05-26",
        "open": 4.912,
        "close": 4.972,
        "high": 4.975,
        "low": 4.91,
        "volume": 9686751,
        "amount": 4786813.58
      },
      "change_pct": 0.71,
      "metrics": {
        "ma5": 4.89,
        "ma10": 4.9007,
        "ma20": 4.88,
        "volatility_20d": 1.44
      }
    },
    "511010.SH": {
      "name": "国债ETF",
      "layer": "hedge",
      "category": "债券",
      "latest": {
        "date": "2026-05-26",
        "open": 141.176,
        "close": 141.23,
        "high": 141.235,
        "low": 141.176,
        "volume": 10170,
        "amount": 143613.19
      },
      "change_pct": 0.04,
      "metrics": {
        "ma5": 141.2158,
        "ma10": 141.1536,
        "ma20": 141.0066,
        "volatility_20d": 0.12
      }
    }
  }
}